[
    {
        "name": "accelerometer.py",
        "dirs": [
            "microbit"
        ],
        "extDirs": [
            "Microbit-Basic-Stubs-main",
            "microbit"
        ],
        "hash": "8ac02f8db819dd4be3772870104ab62d0fafaddb1c30c3353c6efe279632c213"
    },
    {
        "name": "compass.py",
        "dirs": [
            "microbit"
        ],
        "extDirs": [
            "Microbit-Basic-Stubs-main",
            "microbit"
        ],
        "hash": "e72c6f4cb360a0dcad7ea61916fba6a63b0e09d7034a257d921d1a0d509e03bc"
    },
    {
        "name": "display.py",
        "dirs": [
            "microbit"
        ],
        "extDirs": [
            "Microbit-Basic-Stubs-main",
            "microbit"
        ],
        "hash": "e198ea937931e893cf0c6813b6351df4d08fcf57d99f6bcd14a565c20c555c7a"
    },
    {
        "name": "i2c.py",
        "dirs": [
            "microbit"
        ],
        "extDirs": [
            "Microbit-Basic-Stubs-main",
            "microbit"
        ],
        "hash": "7a11a15bd2808efd73f074ae00684da89dff5f53ccda60b786a19a35b8538e8a"
    },
    {
        "name": "microphone.py",
        "dirs": [
            "microbit"
        ],
        "extDirs": [
            "Microbit-Basic-Stubs-main",
            "microbit"
        ],
        "hash": "276a625e1f2ea0bf4e5fa0ea9c7fe2fbfe79f17989615f5624a104f36b42ee7f"
    },
    {
        "name": "power.py",
        "dirs": [
            "microbit"
        ],
        "extDirs": [
            "Microbit-Basic-Stubs-main",
            "microbit"
        ],
        "hash": "ec1375a89621a0be2cdee12d6f1442cdbfe1177e5027eb305181dcd4ba816c80"
    },
    {
        "name": "speaker.py",
        "dirs": [
            "microbit"
        ],
        "extDirs": [
            "Microbit-Basic-Stubs-main",
            "microbit"
        ],
        "hash": "35b5734d29901552a12cf05c23ab6d6ba931910fd11f77ea5eef4c241f0d4271"
    },
    {
        "name": "spi.py",
        "dirs": [
            "microbit"
        ],
        "extDirs": [
            "Microbit-Basic-Stubs-main",
            "microbit"
        ],
        "hash": "8c7cfb7e917f78621bcd1bdc9748887831ff6bc4773139460c46ba928cd3fb9a"
    },
    {
        "name": "uart.py",
        "dirs": [
            "microbit"
        ],
        "extDirs": [
            "Microbit-Basic-Stubs-main",
            "microbit"
        ],
        "hash": "7fefc62b90a9a458ee6cb30d7b1155269d41928b44f869df3e145ef386b53266"
    },
    {
        "name": "__init__.py",
        "dirs": [
            "microbit"
        ],
        "extDirs": [
            "Microbit-Basic-Stubs-main",
            "microbit"
        ],
        "hash": "a808859229c5cdd55b894662c51d4f57a1760c18f0ee7e79e65aec31fe6abf5f"
    },
    {
        "name": "__init__.py",
        "dirs": [
            "audio"
        ],
        "extDirs": [
            "Microbit-Extended-Stubs-main",
            "audio"
        ],
        "hash": "4cbb6913e9b2033ae90aa3a50b0ac56f0a9a86000808d094f09fed29fe5eeb69"
    },
    {
        "name": "__init__.py",
        "dirs": [
            "log"
        ],
        "extDirs": [
            "Microbit-Extended-Stubs-main",
            "log"
        ],
        "hash": "d2e69ac24552a8a403f190ce25b75f96e90927eb417cd940474911897edf8fc6"
    },
    {
        "name": "__init__.py",
        "dirs": [
            "machine"
        ],
        "extDirs": [
            "Microbit-Extended-Stubs-main",
            "machine"
        ],
        "hash": "7fbf7b144ab1d52f439339b0f0a204fe9e6f63e57ef7748627e22c0e4a032b6d"
    },
    {
        "name": "__init__.py",
        "dirs": [
            "music"
        ],
        "extDirs": [
            "Microbit-Extended-Stubs-main",
            "music"
        ],
        "hash": "b03ef2b0ce29973ba2cd6d2273dafd41076677986403c35eb591fdf50a62adaa"
    },
    {
        "name": "__init__.py",
        "dirs": [
            "neopixel"
        ],
        "extDirs": [
            "Microbit-Extended-Stubs-main",
            "neopixel"
        ],
        "hash": "a27283b999e204fc8209a62399f7457592cea1893d0508eb3ce5a5177f72d4db"
    },
    {
        "name": "__init__.py",
        "dirs": [
            "os"
        ],
        "extDirs": [
            "Microbit-Extended-Stubs-main",
            "os"
        ],
        "hash": "4d6d9a719abd727cb92e732a7795d3c2744e16742c9cffed9f86db15dda7fd19"
    },
    {
        "name": "__init__.py",
        "dirs": [
            "radio"
        ],
        "extDirs": [
            "Microbit-Extended-Stubs-main",
            "radio"
        ],
        "hash": "4229f3a2a3b9756c610e21aafbed9736502e40d42f6b80248ee785d78ac6dfd2"
    },
    {
        "name": "__init__.py",
        "dirs": [
            "random"
        ],
        "extDirs": [
            "Microbit-Extended-Stubs-main",
            "random"
        ],
        "hash": "04d3c2ae5e526ab85b71e966b9dfeeb6f72c2650aa9d66a38008bd3a990b0284"
    },
    {
        "name": "__init__.py",
        "dirs": [
            "speech"
        ],
        "extDirs": [
            "Microbit-Extended-Stubs-main",
            "speech"
        ],
        "hash": "c0eccfaa7f76430766c483fbe9a767670e0b9633c1cc3b278403732afcd87565"
    },
    {
        "name": "__init__.py",
        "dirs": [
            "utime"
        ],
        "extDirs": [
            "Microbit-Extended-Stubs-main",
            "utime"
        ],
        "hash": "76988493f949903172faae38b61eca41617d2a0b1c6a3cdec45251ef3cd4eb32"
    }
]